langchain_notion/__init__.py
langchain_notion/notion_wrapper.py
langchain_notion/py.typed
langchain_notion/toolkits.py
langchain_notion/tools.py
langchain_notion-0.1.1.dist-info/LICENSE
langchain_notion-0.1.1.dist-info/METADATA
langchain_notion-0.1.1.dist-info/WHEEL
langchain_notion-0.1.1.dist-info/RECORD
