Metadata-Version: 2.3
Name: langchain-notion
Version: 0.1.1
Summary: LangChain Tools & Toolkit for Notion (search pages, get page, create page).
License: MIT
Author: Rujeet
Author-email: r1jahagirdar@gmail.com
Requires-Python: >=3.9,<4.0
Classifier: License :: OSI Approved :: MIT License
Classifier: Programming Language :: Python :: 3
Classifier: Programming Language :: Python :: 3.9
Classifier: Programming Language :: Python :: 3.10
Classifier: Programming Language :: Python :: 3.11
Classifier: Programming Language :: Python :: 3.12
Classifier: Programming Language :: Python :: 3.13
Provides-Extra: test
Requires-Dist: langchain-core (>=0.3.15,<0.4.0)
Requires-Dist: notion-client (>=2.4.0,<3.0.0)
Project-URL: Repository, https://github.com/rujeetjahagirdar/langchain-notion
